tf_convex_polygon_iou/__init__.py
tf_convex_polygon_iou/_data.py
tf_convex_polygon_iou/_numpy_implementation.py
tf_convex_polygon_iou/_tf_implementation.py
tf_convex_polygon_iou/test_numpy.py
tf_convex_polygon_iou/test_tensorflow.py
tf_convex_polygon_iou_atuleu-0.0.2.dist-info/LICENSE
tf_convex_polygon_iou_atuleu-0.0.2.dist-info/METADATA
tf_convex_polygon_iou_atuleu-0.0.2.dist-info/WHEEL
tf_convex_polygon_iou_atuleu-0.0.2.dist-info/top_level.txt
tf_convex_polygon_iou_atuleu-0.0.2.dist-info/RECORD
