Metadata-Version: 2.1
Name: tf-convex-polygon-iou-atuleu
Version: 0.0.2
Summary: IoU computation for convex polygons
Home-page: https://github.com/atuleu/tf-convex-polygon-iou
Author: Alexandre Tuleu
Author-email: alexandre.tuleu.2005@polytechnique.org
License: UNKNOWN
Project-URL: Bug Tracker, https://github.com/atuleu/tf-convex-polygon-iou
Platform: UNKNOWN
Classifier: Programming Language :: Python :: 3
Classifier: License :: OSI Approved :: MIT License
Classifier: Operating System :: OS Independent
Requires-Python: >=3.6
License-File: LICENSE
Requires-Dist: tensorflow (>=2.6.0)
